ultrasync_mcp/__init__.py
ultrasync_mcp/_entry.py
ultrasync_mcp/call_graph.py
ultrasync_mcp/cli/__init__.py
ultrasync_mcp/cli/_common.py
ultrasync_mcp/cli/commands/__init__.py
ultrasync_mcp/cli/commands/anchors.py
ultrasync_mcp/cli/commands/callgraph.py
ultrasync_mcp/cli/commands/compact.py
ultrasync_mcp/cli/commands/conventions.py
ultrasync_mcp/cli/commands/delete.py
ultrasync_mcp/cli/commands/enrich.py
ultrasync_mcp/cli/commands/graph.py
ultrasync_mcp/cli/commands/grep.py
ultrasync_mcp/cli/commands/index.py
ultrasync_mcp/cli/commands/ir.py
ultrasync_mcp/cli/commands/keys.py
ultrasync_mcp/cli/commands/mcp.py
ultrasync_mcp/cli/commands/memory.py
ultrasync_mcp/cli/commands/patterns.py
ultrasync_mcp/cli/commands/query.py
ultrasync_mcp/cli/commands/repl.py
ultrasync_mcp/cli/commands/show.py
ultrasync_mcp/cli/commands/source.py
ultrasync_mcp/cli/commands/stack.py
ultrasync_mcp/cli/commands/stats.py
ultrasync_mcp/cli/commands/threads.py
ultrasync_mcp/cli/commands/voyager.py
ultrasync_mcp/cli/commands/warm.py
ultrasync_mcp/console.py
ultrasync_mcp/embeddings.py
ultrasync_mcp/enrich.py
ultrasync_mcp/events.py
ultrasync_mcp/file_registry.py
ultrasync_mcp/file_scanner.py
ultrasync_mcp/git.py
ultrasync_mcp/graph/__init__.py
ultrasync_mcp/graph/adjacency.py
ultrasync_mcp/graph/bootstrap.py
ultrasync_mcp/graph/relations.py
ultrasync_mcp/graph/storage.py
ultrasync_mcp/hyperscan_search.py
ultrasync_mcp/index_builder.py
ultrasync_mcp/ir.py
ultrasync_mcp/jit/__init__.py
ultrasync_mcp/jit/blob.py
ultrasync_mcp/jit/cache.py
ultrasync_mcp/jit/convention_discovery.py
ultrasync_mcp/jit/conventions.py
ultrasync_mcp/jit/embed_queue.py
ultrasync_mcp/jit/lexical.py
ultrasync_mcp/jit/lmdb_tracker.py
ultrasync_mcp/jit/manager.py
ultrasync_mcp/jit/memory.py
ultrasync_mcp/jit/memory_extractor.py
ultrasync_mcp/jit/progress.py
ultrasync_mcp/jit/recency.py
ultrasync_mcp/jit/search.py
ultrasync_mcp/jit/secrets.py
ultrasync_mcp/jit/session_threads.py
ultrasync_mcp/jit/vector_store.py
ultrasync_mcp-1.0.1.dist-info/WHEEL
ultrasync_mcp-1.0.1.dist-info/entry_points.txt
ultrasync_mcp-1.0.1.dist-info/METADATA
ultrasync_mcp-1.0.1.dist-info/RECORD
