Metadata-Version: 2.3
Name: ultrasync-mcp
Version: 1.0.1
Summary: Semantic code indexing and memory for AI coding agents
Keywords: ai,coding-agent,embeddings,mcp,semantic-search
Author: David Gidwani
Author-email: David Gidwani <david.gidwani@gmail.com>
License: MIT
Classifier: Development Status :: 3 - Alpha
Classifier: Intended Audience :: Developers
Classifier: License :: OSI Approved :: MIT License
Classifier: Programming Language :: Python :: 3
Classifier: Programming Language :: Python :: 3.10
Classifier: Programming Language :: Python :: 3.11
Classifier: Programming Language :: Python :: 3.12
Classifier: Programming Language :: Python :: 3.13
Classifier: Programming Language :: Python :: 3.14
Classifier: Topic :: Software Development :: Libraries :: Python Modules
Requires-Dist: hyperscan>=0.8.0
Requires-Dist: lmdb>=1.5.1
Requires-Dist: mcp>=1.2.0
Requires-Dist: msgpack>=1.1.0
Requires-Dist: numpy>=1.24
Requires-Dist: rich>=14.2.0
Requires-Dist: sentence-transformers>=3
Requires-Dist: structlog>=24.0
Requires-Dist: tyro>=0.9
Requires-Dist: ultrasync-index
Requires-Dist: urllib3>=2.6.0
Requires-Dist: pyyaml>=6.0 ; extra == 'benchmark'
Requires-Dist: rich>=13.0 ; extra == 'cli'
Requires-Dist: textual>=0.50 ; extra == 'cli'
Requires-Dist: httpx>=0.27 ; extra == 'infinity'
Requires-Dist: tantivy>=0.22 ; extra == 'lexical'
Requires-Dist: detect-secrets>=1.4.0 ; extra == 'secrets'
Requires-Dist: python-socketio[asyncio-client]>=5.11.0 ; extra == 'sync'
Requires-Dist: aiohttp>=3.9.0 ; extra == 'sync'
Requires-Python: >=3.10
Project-URL: Homepage, https://github.com/davidgidwani/ultrasync
Project-URL: Repository, https://github.com/davidgidwani/ultrasync
Provides-Extra: benchmark
Provides-Extra: cli
Provides-Extra: infinity
Provides-Extra: lexical
Provides-Extra: secrets
Provides-Extra: sync
